ease_dggs/__init__.py
ease_dggs/constants.py
ease_dggs/grid_align.py
ease_dggs/logConfig.py
ease_dggs/dggs/__init__.py
ease_dggs/dggs/checks.py
ease_dggs/dggs/grid_addressing.py
ease_dggs/dggs/hierarchy.py
ease_dggs/dggs/transforms.py
ease_dggs/dggs/utils.py
ease_dggs-0.1.0.dist-info/licenses/LICENSE
tests/__init__.py
tests/conftest.py
tests/test_constants.py
tests/test_dggs_checks.py
tests/test_dggs_grid_addressing.py
tests/test_dggs_hierarchy.py
tests/test_dggs_transforms.py
tests/test_dggs_utils.py
tests/test_grid_align.py
ease_dggs-0.1.0.dist-info/METADATA
ease_dggs-0.1.0.dist-info/WHEEL
ease_dggs-0.1.0.dist-info/top_level.txt
ease_dggs-0.1.0.dist-info/RECORD
