Metadata-Version: 2.4
Name: ease-dggs
Version: 0.1.0
Summary: Python utilities for EASE-based discrete global grid systems
Home-page: https://github.com/GEMS-UMN/EASE-DGGS
Author: GEMS Geospatial Developers
Author-email: GEMS Geospatial Developers <gemssupport@umn.edu>
License: Apache-2.0
Project-URL: Homepage, https://github.com/GEMS-UMN/EASE-DGGS
Project-URL: Repository, https://github.com/GEMS-UMN/EASE-DGGS
Classifier: Programming Language :: Python :: 3
Classifier: License :: OSI Approved :: Apache Software License
Classifier: Operating System :: OS Independent
Classifier: Development Status :: 3 - Alpha
Classifier: Intended Audience :: Science/Research
Classifier: Topic :: Scientific/Engineering :: GIS
Requires-Python: >=3.9
License-File: LICENSE
Dynamic: author
Dynamic: home-page
Dynamic: license-file
Dynamic: requires-python
